resolver/__init__.py
resolver/file.py
sceptre_file_resolver-1.0.6.dist-info/LICENSE
sceptre_file_resolver-1.0.6.dist-info/METADATA
sceptre_file_resolver-1.0.6.dist-info/WHEEL
sceptre_file_resolver-1.0.6.dist-info/entry_points.txt
sceptre_file_resolver-1.0.6.dist-info/top_level.txt
sceptre_file_resolver-1.0.6.dist-info/RECORD
