Metadata-Version: 2.1
Name: sceptre-file-resolver
Version: 1.0.6
Summary: A Sceptre resolver to retrieve file content
Home-page: https://github.com/sceptre/sceptre-file-resolver
Author: zaro0508
Author-email: zaro0508@gmail.com
License: Apache2
Keywords: sceptre,sceptre-resolver
Platform: UNKNOWN
Classifier: Intended Audience :: Developers
Classifier: Natural Language :: English
Classifier: Environment :: Console
Classifier: Programming Language :: Python :: 3.6
Classifier: Programming Language :: Python :: 3.7
Requires-Dist: requests (<3,>=2.25)
Requires-Dist: sceptre (>=2.7)
Provides-Extra: test
Requires-Dist: pytest (>=3.2) ; extra == 'test'
